[{"timestamp":1595416242385,"files":[{"filename":"ssr-bundle.6e806.css","previous":566,"size":0,"diff":-566},{"filename":"ssr-bundle.js","previous":3665,"size":0,"diff":-3665},{"filename":"bundle.7e56a.css","previous":0,"size":445,"diff":445},{"filename":"bundle.*****.esm.js","previous":0,"size":8346,"diff":8346},{"filename":"polyfills.*****.esm.js","previous":0,"size":1969,"diff":1969},{"filename":"route-home.chunk.e6c71.css","previous":0,"size":74,"diff":74},{"filename":"route-home.chunk.*****.esm.js","previous":0,"size":246,"diff":246},{"filename":"route-profile.chunk.62c75.css","previous":0,"size":77,"diff":77},{"filename":"route-profile.chunk.*****.esm.js","previous":0,"size":517,"diff":517},{"filename":"sw.js","previous":0,"size":8266,"diff":8266},{"filename":"sw-esm.js","previous":0,"size":8266,"diff":8266},{"filename":"bundle.7e38b.js","previous":0,"size":8418,"diff":8418},{"filename":"polyfills.694cb.js","previous":0,"size":2013,"diff":2013},{"filename":"route-home.chunk.f6843.js","previous":0,"size":292,"diff":292},{"filename":"route-profile.chunk.a1574.js","previous":0,"size":681,"diff":681}]},{"timestamp":1595416236395,"files":[{"filename":"bundle.7e56a.css","previous":445,"size":0,"diff":-445},{"filename":"bundle.*****.esm.js","previous":8346,"size":0,"diff":-8346},{"filename":"polyfills.*****.esm.js","previous":1969,"size":0,"diff":-1969},{"filename":"route-home.chunk.e6c71.css","previous":74,"size":0,"diff":-74},{"filename":"route-home.chunk.*****.esm.js","previous":246,"size":0,"diff":-246},{"filename":"route-profile.chunk.62c75.css","previous":77,"size":0,"diff":-77},{"filename":"route-profile.chunk.*****.esm.js","previous":517,"size":0,"diff":-517},{"filename":"sw.js","previous":8266,"size":0,"diff":-8266},{"filename":"sw-esm.js","previous":8266,"size":0,"diff":-8266},{"filename":"bundle.7e38b.js","previous":8418,"size":0,"diff":-8418},{"filename":"polyfills.694cb.js","previous":2013,"size":0,"diff":-2013},{"filename":"route-home.chunk.f6843.js","previous":292,"size":0,"diff":-292},{"filename":"route-profile.chunk.a1574.js","previous":681,"size":0,"diff":-681},{"filename":"ssr-bundle.6e806.css","previous":0,"size":566,"diff":566},{"filename":"ssr-bundle.js","previous":0,"size":3665,"diff":3665}]},{"timestamp":1595416151298,"files":[{"filename":"ssr-bundle.6e806.css","previous":566,"size":0,"diff":-566},{"filename":"ssr-bundle.js","previous":3665,"size":0,"diff":-3665},{"filename":"bundle.7e56a.css","previous":0,"size":445,"diff":445},{"filename":"bundle.*****.esm.js","previous":0,"size":8346,"diff":8346},{"filename":"polyfills.*****.esm.js","previous":0,"size":1969,"diff":1969},{"filename":"route-home.chunk.e6c71.css","previous":0,"size":74,"diff":74},{"filename":"route-home.chunk.*****.esm.js","previous":0,"size":246,"diff":246},{"filename":"route-profile.chunk.62c75.css","previous":0,"size":77,"diff":77},{"filename":"route-profile.chunk.*****.esm.js","previous":0,"size":517,"diff":517},{"filename":"sw.js","previous":0,"size":8266,"diff":8266},{"filename":"sw-esm.js","previous":0,"size":8266,"diff":8266},{"filename":"bundle.7e38b.js","previous":0,"size":8418,"diff":8418},{"filename":"polyfills.694cb.js","previous":0,"size":2013,"diff":2013},{"filename":"route-home.chunk.f6843.js","previous":0,"size":292,"diff":292},{"filename":"route-profile.chunk.a1574.js","previous":0,"size":681,"diff":681}]},{"timestamp":1595416145192,"files":[{"filename":"bundle.7e56a.css","previous":445,"size":0,"diff":-445},{"filename":"bundle.*****.esm.js","previous":8346,"size":0,"diff":-8346},{"filename":"polyfills.*****.esm.js","previous":1969,"size":0,"diff":-1969},{"filename":"route-home.chunk.e6c71.css","previous":74,"size":0,"diff":-74},{"filename":"route-home.chunk.*****.esm.js","previous":246,"size":0,"diff":-246},{"filename":"route-profile.chunk.62c75.css","previous":77,"size":0,"diff":-77},{"filename":"route-profile.chunk.*****.esm.js","previous":517,"size":0,"diff":-517},{"filename":"sw.js","previous":8266,"size":0,"diff":-8266},{"filename":"sw-esm.js","previous":8266,"size":0,"diff":-8266},{"filename":"bundle.7e38b.js","previous":8418,"size":0,"diff":-8418},{"filename":"polyfills.694cb.js","previous":2013,"size":0,"diff":-2013},{"filename":"route-home.chunk.f6843.js","previous":292,"size":0,"diff":-292},{"filename":"route-profile.chunk.a1574.js","previous":681,"size":0,"diff":-681},{"filename":"ssr-bundle.6e806.css","previous":0,"size":566,"diff":566},{"filename":"ssr-bundle.js","previous":0,"size":3665,"diff":3665}]},{"timestamp":1595415589268,"files":[{"filename":"ssr-bundle.6e806.css","previous":566,"size":0,"diff":-566},{"filename":"ssr-bundle.js","previous":3665,"size":0,"diff":-3665},{"filename":"bundle.7e56a.css","previous":0,"size":445,"diff":445},{"filename":"bundle.*****.esm.js","previous":0,"size":8346,"diff":8346},{"filename":"polyfills.*****.esm.js","previous":0,"size":1969,"diff":1969},{"filename":"route-home.chunk.e6c71.css","previous":0,"size":74,"diff":74},{"filename":"route-home.chunk.*****.esm.js","previous":0,"size":246,"diff":246},{"filename":"route-profile.chunk.62c75.css","previous":0,"size":77,"diff":77},{"filename":"route-profile.chunk.*****.esm.js","previous":0,"size":517,"diff":517},{"filename":"sw.js","previous":0,"size":8266,"diff":8266},{"filename":"sw-esm.js","previous":0,"size":8266,"diff":8266},{"filename":"bundle.7e38b.js","previous":0,"size":8418,"diff":8418},{"filename":"polyfills.694cb.js","previous":0,"size":2013,"diff":2013},{"filename":"route-home.chunk.f6843.js","previous":0,"size":292,"diff":292},{"filename":"route-profile.chunk.a1574.js","previous":0,"size":681,"diff":681}]},{"timestamp":1595415580117,"files":[{"filename":"ssr-bundle.6e806.css","previous":0,"size":566,"diff":566},{"filename":"ssr-bundle.js","previous":0,"size":3665,"diff":3665}]}]
